README.rst
setup.py
flask_ext_migrate/__init__.py
flask_ext_migrate/startup.py
flask_ext_migrate.egg-info/PKG-INFO
flask_ext_migrate.egg-info/SOURCES.txt
flask_ext_migrate.egg-info/dependency_links.txt
flask_ext_migrate.egg-info/entry_points.txt
flask_ext_migrate.egg-info/pbr.json
flask_ext_migrate.egg-info/requires.txt
flask_ext_migrate.egg-info/top_level.txt