Metadata-Version: 1.0
Name: flask-ext-migrate
Version: 1.0.0
Summary: A sourcecode manipulation tool for converting imports.
Home-page: https://github.com/pallets/flask-ext-migrate
Author: Keyan Pishdadian
Author-email: kpishdadian@gmail.com
License: BSD
Platform: UNKNOWN
